rabbitmq_async_client/__init__.py
rabbitmq_async_client/rabbitmq_client.py
tests/__init__.py
tests/conf_rabbit.py
tests/cosumer.py
tests/init_queues.py
tests/publisher.py
tests/pull.py
tests/push.py
client_async_rabbitmq-0.1.0.dist-info/LICENSE
client_async_rabbitmq-0.1.0.dist-info/METADATA
client_async_rabbitmq-0.1.0.dist-info/WHEEL
client_async_rabbitmq-0.1.0.dist-info/top_level.txt
client_async_rabbitmq-0.1.0.dist-info/RECORD
